SRinputs/FRinputs.py
SRinputs/SRinputs.py
SRinputs/__init__.py
srinputs-0.1.1.dist-info/licenses/LICENSE.txt
srinputs-0.1.1.dist-info/METADATA
srinputs-0.1.1.dist-info/WHEEL
srinputs-0.1.1.dist-info/top_level.txt
srinputs-0.1.1.dist-info/RECORD
