Metadata-Version: 2.4
Name: SRinputs
Version: 0.1.1
Summary: A small Python package that improves the usage of the built-in input() function with functionalities such as static and multiple inputs.
Author-email: Keiner Mendoza <keynerismo@gmail.com>
Project-URL: Homepage, https://github.com/keyles-Py/SRinputs
Classifier: Programming Language :: Python :: 3
Classifier: License :: OSI Approved :: MIT License
Classifier: Operating System :: OS Independent
Requires-Python: >=3.7
License-File: LICENSE.txt
Requires-Dist: fast_langdetect
Dynamic: license-file
